ptpython/__init__.py
ptpython/__main__.py
ptpython/completer.py
ptpython/eventloop.py
ptpython/filters.py
ptpython/history_browser.py
ptpython/ipython.py
ptpython/key_bindings.py
ptpython/layout.py
ptpython/lexer.py
ptpython/printer.py
ptpython/prompt_style.py
ptpython/py.typed
ptpython/python_input.py
ptpython/repl.py
ptpython/signatures.py
ptpython/style.py
ptpython/utils.py
ptpython/validator.py
ptpython/contrib/__init__.py
ptpython/contrib/asyncssh_repl.py
ptpython/entry_points/__init__.py
ptpython/entry_points/run_ptipython.py
ptpython/entry_points/run_ptpython.py
ptpython_aioipfs-3.0.27.dist-info/LICENSE
ptpython_aioipfs-3.0.27.dist-info/METADATA
ptpython_aioipfs-3.0.27.dist-info/WHEEL
ptpython_aioipfs-3.0.27.dist-info/entry_points.txt
ptpython_aioipfs-3.0.27.dist-info/top_level.txt
ptpython_aioipfs-3.0.27.dist-info/RECORD
